tantheta/__init__.py
tantheta/algebra.py
tantheta/calculus.py
tantheta/chemistry.py
tantheta/core.py
tantheta/geometry.py
tantheta/linear_algebra.py
tantheta/maths.py
tantheta/physics.py
tantheta/plot.py
tantheta/probability.py
tantheta/stats.py
tantheta/trigonometry.py
tantheta-1.1.0.dist-info/licenses/LICENSE.txt
tantheta-1.1.0.dist-info/METADATA
tantheta-1.1.0.dist-info/WHEEL
tantheta-1.1.0.dist-info/top_level.txt
tantheta-1.1.0.dist-info/RECORD
