Metadata-Version: 2.4
Name: tantheta
Version: 1.1.0
Summary: A versatile Python library for symbolic computation and problem solving in mathematics, physics, and chemistry — covering algebra, calculus, mechanics, thermodynamics, stoichiometry, and kinetics.
Home-page: https://github.com/Ayushparwal/tantheta
Author: Ayush Parwal
Author-email: Ayush Parwal <ayushparwal777@gmail.com>
License-Expression: MIT
Project-URL: Source, https://github.com/Ayushparwal/tantheta
Keywords: symbolic math,algebra,calculus,trigonometry,math toolkit,math solver,sympy,mathematics,cli tool,math automation,math library,python math,differentiation,integration
Classifier: Intended Audience :: Developers
Classifier: Operating System :: OS Independent
Classifier: Programming Language :: Python :: 3
Classifier: Programming Language :: Python :: 3.9
Classifier: Programming Language :: Python :: 3.10
Classifier: Programming Language :: Python :: 3.11
Classifier: Programming Language :: Python :: 3.12
Classifier: Topic :: Software Development :: Libraries :: Python Modules
Requires-Python: >=3.7
License-File: LICENSE.txt
Requires-Dist: sympy>=1.12
Dynamic: author
Dynamic: home-page
Dynamic: license-file
Dynamic: requires-python
